{"guide_annotations.md":"225f120f","guide_attributes.md":"ab0873d9","guide_common-techniques.md":"e0bfa84b","guide_cookbook.md":"eb5d1974","guide_faq.md":"79f5dd7f","guide_generating-openapi-documents.md":"f7889e0c","guide_index.md":"9c6e66f2","guide_installation.md":"a175ede2","guide_migrating-to-v3.md":"1feb96f8","guide_migrating-to-v4.md":"8b266b57","guide_required-elements.md":"fb6c3a58","guide_under-the-hood.md":"296342e7","index.md":"d8a2e23c","reference_annotations.md":"a4c518ba","reference_attributes.md":"a55852ed","reference_generator.md":"c8231d4c","reference_index.md":"ba4ab930","reference_processors.md":"6300dab1","related-projects.md":"84464cef"}
